{
  "visits": [
    {
      "id": 1,
      "residentId": 1,
      "visitingLocationId": 1,
      "visitorName": "Edgar Fabricio Amador Santos",
      "dateIn": "11/10/2019 07:00",
      "dateOut": "11/10/2019 5:00 PM",
      "idNumber": "0504198200201",
      "typeOfVisit": "Visita",
      "notes": "",
      "status": "ACTIVO"
    },
    {
      "dateIn": "2019-11-10T19:06:43.317Z",
      "visitorName": "Valeria Amador",
      "idNumber": "05042001200565",
      "typeOfVisit": "Amigo o Familiar",
      "notes": "Se quedara una semana completa",
      "residentId": 1,
      "visitingLocationId": 1,
      "status": "ACTIVO",
      "id": 2
    }
  ]
}